fastgcp/BigQuery.py
fastgcp/CloudFunctions.py
fastgcp/__init__.py
fastgcp-0.1.1.dist-info/licenses/LICENSE.md
fastgcp-0.1.1.dist-info/METADATA
fastgcp-0.1.1.dist-info/WHEEL
fastgcp-0.1.1.dist-info/top_level.txt
fastgcp-0.1.1.dist-info/RECORD
