Metadata-Version: 2.4
Name: fastgcp
Version: 0.1.1
Summary: The faster, more intuitive way of working with Google Cloud Platform services and frameworks
Home-page: https://tomathon.dev/articles/fastgcp
Author: tomathon
Author-email: tomathon.dev@pm.me
Project-URL: Bug Tracker, https://codeberg.org/tomathon/fastgcp/issues
Classifier: Programming Language :: Python :: 3
Classifier: License :: OSI Approved :: MIT License
Classifier: Operating System :: OS Independent
Requires-Python: >=3.6
License-File: LICENSE.md
Dynamic: license-file
